{
  "publicPath": "/assets/",
  "all": [
    "pages/index.67886538e29db1bcbbc7.js.map",
    "pages/index.67886538e29db1bcbbc7.js",
    "common.59b24e9921e1a43ecf5c.js",
    "app.493188554bc8a07df1d6.js",
    "manifest.ada4b8c733cdeeef5857.js",
    "common.bc35257661150fa55f19fa5726fe83ae.css",
    "LICENSES",
    "layouts/default.045250d5c281b31a97e1.js",
    "layouts/default.045250d5c281b31a97e1.js.map",
    "common.59b24e9921e1a43ecf5c.js.map",
    "app.493188554bc8a07df1d6.js.map",
    "common.bc35257661150fa55f19fa5726fe83ae.css.map",
    "manifest.ada4b8c733cdeeef5857.js.map",
    "index.spa.html",
    "index.ssr.html"
  ],
  "initial": [
    "manifest.ada4b8c733cdeeef5857.js",
    "common.59b24e9921e1a43ecf5c.js",
    "app.493188554bc8a07df1d6.js"
  ],
  "async": [
    "pages/index.67886538e29db1bcbbc7.js",
    "layouts/default.045250d5c281b31a97e1.js"
  ],
  "modules": {
    "27774793": [
      2,
      9
    ],
    "35942899": [
      3,
      5,
      10,
      11
    ],
    "51030666": [
      2,
      9
    ],
    "69818044": [
      3,
      5,
      10,
      11
    ],
    "80860580": [
      1,
      0
    ],
    "86698686": [
      2,
      9
    ],
    "5b5cf573": [
      3,
      5,
      10,
      11
    ],
    "c6f39eae": [
      2,
      9
    ],
    "2e0f67f8": [
      1,
      0
    ],
    "445bd486": [
      2,
      9
    ],
    "443d9d76": [
      2,
      9
    ],
    "4f59cde3": [
      2,
      9
    ],
    "b513dffe": [
      2,
      9
    ],
    "046bb3a2": [
      7,
      8
    ],
    "01c512b4": [
      1,
      0
    ],
    "6e74dba8": [
      2,
      9
    ],
    "78ed1db8": [
      2,
      9
    ],
    "1f3108d2": [
      2,
      9
    ],
    "3e624a7c": [
      2,
      9
    ],
    "b80d6878": [
      1,
      0
    ],
    "ce12de98": [
      2,
      9
    ],
    "93b360b6": [
      3,
      5,
      10,
      11
    ],
    "65b74fb8": [
      2,
      9
    ],
    "626ef5bd": [
      2,
      9
    ],
    "1cd8e954": [
      2,
      9
    ],
    "4165a850": [
      2,
      9
    ],
    "7f6fda64": [
      2,
      9
    ],
    "4f99c4d0": [
      2,
      9
    ],
    "68a62364": [
      2,
      9
    ],
    "eee8e4c4": [
      2,
      9
    ],
    "5a7fddeb": [
      2,
      9
    ],
    "55681eb8": [
      2,
      9
    ],
    "2b463933": [
      2,
      9
    ],
    "cb6e99c8": [
      2,
      9
    ],
    "2ae4416f": [
      3,
      5,
      10,
      11
    ],
    "c2d4ffcc": [
      2,
      9
    ],
    "69a5c240": [
      3,
      5,
      10,
      11
    ],
    "647581b8": [
      3,
      5,
      10,
      11
    ],
    "ef65d76a": [
      2,
      9
    ],
    "b8d1c954": [
      2,
      9
    ],
    "5f82e033": [
      3,
      5,
      10,
      11
    ],
    "316439f9": [
      2,
      9
    ],
    "dc5c72ea": [
      2,
      9
    ],
    "98fbc83a": [
      2,
      9
    ],
    "56f66d82": [
      7,
      8
    ],
    "fef6086a": [
      3,
      5,
      10,
      11
    ],
    "4bd60b33": [
      2,
      9
    ],
    "5cdd96d2": [
      2,
      9
    ],
    "3409c341": [
      2,
      9
    ],
    "27a12f8c": [
      2,
      9
    ],
    "17e74dc9": [
      3,
      5,
      10,
      11
    ],
    "58168b35": [
      2,
      9
    ],
    "1c9cd1ea": [
      2,
      9
    ],
    "5a885e96": [
      2,
      9
    ],
    "3e5a12a2": [
      2,
      9
    ],
    "a6b444b6": [
      3,
      5,
      10,
      11
    ],
    "1fc950c2": [
      3,
      5,
      10,
      11
    ],
    "3c280539": [
      2,
      9
    ],
    "26a2b68c": [
      2,
      9
    ],
    "ac5e0a08": [
      2,
      9
    ],
    "ce2081ba": [
      2,
      9
    ],
    "58445f14": [
      2,
      9
    ],
    "4688ac88": [
      1,
      0
    ],
    "d50731b6": [
      2,
      9
    ],
    "140fcf9a": [
      2,
      9
    ],
    "0face9cc": [
      7,
      8
    ],
    "77965f9e": [
      2,
      9
    ],
    "56bdbc6c": [
      2,
      9
    ],
    "15ba34aa": [
      3,
      5,
      10,
      11
    ],
    "6b5b2367": [
      1,
      0
    ],
    "70ef0ce6": [
      2,
      9
    ],
    "d61c93da": [
      2,
      9
    ],
    "6ec6f863": [
      2,
      9
    ],
    "cc1b831c": [
      2,
      9
    ],
    "e935444c": [
      2,
      9
    ],
    "21f05a90": [
      2,
      9
    ],
    "401aeaf1": [
      3,
      5,
      10,
      11
    ],
    "5fd28b09": [
      2,
      9
    ],
    "4583da15": [
      2,
      9
    ],
    "78f5136c": [
      2,
      9
    ],
    "73bd0b08": [
      2,
      9
    ],
    "59f119c2": [
      3,
      5,
      10,
      11
    ],
    "440d3053": [
      2,
      9
    ],
    "4f1e2f16": [
      2,
      9
    ],
    "a8981d44": [
      2,
      9
    ],
    "3e82aaf6": [
      2,
      9
    ],
    "5dcbe550": [
      2,
      9
    ],
    "5edacb6c": [
      2,
      9
    ],
    "70f8c498": [
      2,
      9
    ],
    "01a8686a": [
      2,
      9
    ],
    "2774bfa0": [
      2,
      9
    ],
    "c199ac3c": [
      2,
      9
    ],
    "1fdd2acf": [
      3,
      5,
      10,
      11
    ],
    "987b5896": [
      2,
      9
    ],
    "2bcfc23e": [
      2,
      9
    ],
    "22c0d918": [
      2,
      9
    ],
    "17a6f49b": [
      1,
      0
    ],
    "19a80064": [
      2,
      9
    ],
    "2b0ff84d": [
      2,
      9
    ],
    "3d07ba6e": [
      3,
      5,
      10,
      11
    ],
    "7d610763": [
      2,
      9
    ],
    "893b2dfa": [
      2,
      9
    ],
    "0e7430b9": [
      2,
      9
    ],
    "15ae8a68": [
      3,
      5,
      10,
      11
    ],
    "246bf6ca": [
      2,
      9
    ],
    "7536499c": [
      2,
      9
    ],
    "2dc20f58": [
      2,
      9
    ],
    "f84675c0": [
      1,
      0
    ],
    "352cb20c": [
      2,
      9
    ],
    "65fba78e": [
      2,
      9
    ],
    "0785f815": [
      2,
      9
    ],
    "b2b069b0": [
      2,
      9
    ],
    "1327159c": [
      2,
      9
    ],
    "7e48d11a": [
      2,
      9
    ],
    "62a8f77c": [
      2,
      9
    ],
    "6ada1593": [
      2,
      9
    ],
    "dff52020": [
      2,
      9
    ],
    "3c67e41a": [
      2,
      9
    ],
    "d83e8782": [
      2,
      9
    ],
    "34385fac": [
      2,
      9
    ],
    "29cf5228": [
      2,
      9
    ],
    "11e779be": [
      2,
      9
    ],
    "3bd6de1f": [
      2,
      9
    ],
    "1922aadc": [
      2,
      9
    ],
    "0546f786": [
      1,
      0
    ],
    "1517fc84": [
      2,
      9
    ],
    "08252899": [
      2,
      9
    ],
    "21f1807d": [
      2,
      9
    ],
    "eacd9026": [
      2,
      9
    ],
    "09db20a9": [
      2,
      9
    ],
    "53d0ce46": [
      2,
      9
    ],
    "5bfddb0b": [
      2,
      9
    ],
    "5b0c7a90": [
      2,
      9
    ],
    "8d9b8a8c": [
      2,
      9
    ],
    "9e715468": [
      2,
      9
    ],
    "ce176a4e": [
      2,
      9
    ],
    "4f91628b": [
      3,
      5,
      10,
      11
    ],
    "44f6f506": [
      7,
      8
    ],
    "3568f32c": [
      2,
      9
    ],
    "10d77c50": [
      3,
      5,
      10,
      11
    ],
    "5ab5d2a8": [
      2,
      9
    ],
    "0f0d4ced": [
      2,
      9
    ],
    "7a764892": [
      2,
      9
    ],
    "1a7e31c8": [
      2,
      9
    ],
    "0631aa84": [
      2,
      9
    ],
    "38269dce": [
      2,
      9
    ],
    "3c27f799": [
      3,
      5,
      10,
      11
    ],
    "7379c64d": [
      2,
      9
    ],
    "52328d96": [
      3,
      5,
      10,
      11
    ],
    "d05547fc": [
      2,
      9
    ],
    "2a564dfd": [
      2,
      9
    ],
    "5a51a17f": [
      2,
      9
    ],
    "629e580d": [
      2,
      9
    ],
    "b79062f8": [
      3,
      5,
      10,
      11
    ],
    "85039f76": [
      2,
      9
    ],
    "0c448742": [
      2,
      9
    ],
    "7d9930f4": [
      2,
      9
    ],
    "f38454f8": [
      3,
      5,
      10,
      11
    ],
    "39c658fb": [
      2,
      9
    ],
    "986b8a2c": [
      3,
      5,
      10,
      11
    ]
  }
}